<!DOCTYPE suite SYSTEM "https://testng.org/testng-1.0.dtd">

<suite name="RegressionUI" verbose="1">
    <test name="CreateFixB2BConvWithoutPayment">
        <classes>
            <class name="com.ui.CreateDeals.B2B.ManagerCreateDealB2BConvClass" />
            <class name="com.ui.CreateDeals.BuyingControlApproveDeal" />
            <class name="com.ui.CreateDeals.B2B.ManagerApproveDealB2B" />
            <class name="com.ui.CreateDeals.TeamLeadApproveDeal" />
            <class name="com.ui.CreateDeals.AuditorApproveDeal" />
        </classes>
    </test>
   <!--    <test name="Deal CPI">-->
<!--        <classes>-->
<!--            <class name="com.ui.ManagerCreateDealCPI" />-->
<!--            <class name="com.ui.ManagerCreateDealFixZid.BuyingControlApproveDealFixZid" />-->
<!--            <class name="com.ui.ManagerCreateDealFixZid.ManagerApproveDeal" />-->
<!--            <class name="com.ui.ManagerCreateDealFixZid.TeamLeadApproveDealFixZid" />-->
<!--            <class name="com.ui.ManagerCreateDealFixZid.AuditorApproveDealFixZid" />-->
<!--        </classes>-->
<!--    </test>-->
<!--    <test name="Deal CPM">-->
<!--        <classes>-->
<!--            <class name="com.ui.ManagerCreateDealCPM.ManagerCreateDealCPM" />-->
<!--            <class name="com.ui.ManagerCreateDealFixZid.BuyingControlApproveDealFixZid" />-->
<!--            <class name="com.ui.ManagerCreateDealFixZid.ManagerApproveDeal" />-->
<!--            <class name="com.ui.ManagerCreateDealFixZid.TeamLeadApproveDealFixZid" />-->
<!--            <class name="com.ui.ManagerCreateDealFixZid.AuditorApproveDealFixZid" />-->
<!--        </classes>-->
<!--    </test>-->
<!--    <test name="Deal FIX_APP">-->
<!--        <classes>-->
<!--            <class name="com.ui.ManagerCreateDealFixApp" />-->
<!--            <class name="com.ui.ManagerCreateDealFixZid.BuyingControlApproveDealFixZid" />-->
<!--            <class name="com.ui.ManagerCreateDealFixZid.ManagerApproveDeal" />-->
<!--            <class name="com.ui.ManagerCreateDealFixZid.TeamLeadApproveDealFixZid" />-->
<!--            <class name="com.ui.ManagerCreateDealFixZid.AuditorApproveDealFixZid" />-->
<!--        </classes>-->
<!--    </test>-->
<!--    <test name="Deal FIX_SMM">-->
<!--        <classes>-->
<!--            <class name="com.ui.ManagerCreateDealFixSMM.ManagerCreateDealFixSMM" />-->
<!--            <class name="com.ui.ManagerCreateDealFixSMM.BuyingControlApproveFixSMM" />-->
<!--            <class name="com.ui.ManagerCreateDealFixSMM.ManagerApproveFixSMM" />-->
<!--            <class name="com.ui.ManagerCreateDealFixSMM.TeamLeadApproveFixSMM" />-->
<!--            <class name="com.ui.ManagerCreateDealFixSMM.AuditorApproveFixSMM" />-->
<!--        </classes>-->
<!--    </test>-->
<!--    <test name="Deal FIX_ZID">-->
<!--        <classes>-->
<!--            <class name="com.ui.ManagerCreateDealFixZid.ManagerCreateDealFixZid" />-->
<!--            <class name="com.ui.ManagerCreateDealFixZid.BuyingControlApproveDealFixZid" />-->
<!--            <class name="com.ui.ManagerCreateDealFixZid.ManagerApproveDeal" />-->
<!--            <class name="com.ui.ManagerCreateDealFixZid.TeamLeadApproveDealFixZid" />-->
<!--            <class name="com.ui.ManagerCreateDealFixZid.AuditorApproveDealFixZid" />-->
<!--        </classes>-->
<!--    </test>-->

</suite>

